HydroPackage/__init__.py
HydroPackage-1.1.0.dist-info/LICENSE
HydroPackage-1.1.0.dist-info/METADATA
HydroPackage-1.1.0.dist-info/WHEEL
HydroPackage-1.1.0.dist-info/entry_points.txt
HydroPackage-1.1.0.dist-info/top_level.txt
HydroPackage-1.1.0.dist-info/RECORD
