Metadata-Version: 2.1
Name: HydroPackage
Version: 1.1.0
Summary: Package For Hydro
Home-page: UNKNOWN
Author: mxnty
Author-email: silverbotbusiness@protonmail.com
License: MIT
Platform: UNKNOWN
Classifier: License :: OSI Approved :: MIT License
Classifier: Programming Language :: Python :: 3
Classifier: Programming Language :: Python :: 3.7
Requires-Dist: requests
